{
  "publicPath": "/_nuxt/",
  "all": [
    "pages_index.d63c90d565a5a2a884ba.js",
    "layouts_default.1948f1cac7428cc2d12f.js",
    "vendor.ecaeec52b864bc413428.js",
    "app.8d00af978fb1cf644786.js",
    "manifest.98cfba27fda2c5145117.js",
    "LICENSES",
    "index.spa.html"
  ],
  "initial": [
    "manifest.98cfba27fda2c5145117.js",
    "vendor.ecaeec52b864bc413428.js",
    "app.8d00af978fb1cf644786.js"
  ],
  "async": [
    "pages_index.d63c90d565a5a2a884ba.js",
    "layouts_default.1948f1cac7428cc2d12f.js"
  ],
  "modules": {
    "64042909": [
      2
    ],
    "75820450": [
      2
    ],
    "77921724": [
      2
    ],
    "8566ca58": [
      2
    ],
    "703899b1": [
      2
    ],
    "6a1cfa21": [
      2
    ],
    "77db366b": [
      2
    ],
    "71ba39b3": [
      2
    ],
    "1403a16d": [
      3
    ],
    "b2ec11ce": [
      0
    ],
    "5395d493": [
      2
    ],
    "2b3ee650": [
      2
    ],
    "5ec31389": [
      2
    ],
    "26ca5e79": [
      3
    ],
    "e3c3aa9e": [
      2
    ],
    "7bede01a": [
      3
    ],
    "3bded1f2": [
      2
    ],
    "8c860a42": [
      2
    ],
    "f3048c3a": [
      2
    ],
    "3973ecd4": [
      0
    ],
    "e3688a30": [
      2
    ],
    "d55b2a02": [
      2
    ],
    "232e0b4d": [
      2
    ],
    "37c0120f": [
      2
    ],
    "4d1e8410": [
      2
    ],
    "9e64318e": [
      2
    ],
    "4e5f96da": [
      2
    ],
    "a792c8c0": [
      2
    ],
    "8b262ce2": [
      2
    ],
    "7cfcf6e8": [
      2
    ],
    "89e1c572": [
      2
    ],
    "77e55c82": [
      2
    ],
    "7e53d9be": [
      2
    ],
    "1556df5e": [
      2
    ],
    "50cfeb00": [
      2
    ],
    "77b2d05e": [
      2
    ],
    "0bdac5c2": [
      2
    ],
    "21807f39": [
      2
    ],
    "4f4df41c": [
      3
    ],
    "0cc22877": [
      2
    ],
    "c8112aac": [
      2
    ],
    "525ae014": [
      2
    ],
    "56f117ec": [
      3
    ],
    "41d40ac9": [
      2
    ],
    "e3d41a52": [
      2
    ],
    "ddd49cb2": [
      3
    ],
    "113b0c56": [
      3
    ],
    "0b4edb6e": [
      2
    ],
    "b6024736": [
      2
    ],
    "0ce6499e": [
      2
    ],
    "8c93ad64": [
      2
    ],
    "df012382": [
      2
    ],
    "4dcc9ed0": [
      2
    ],
    "08a7425f": [
      2
    ],
    "ff2a29ee": [
      2
    ],
    "4ec497a1": [
      2
    ],
    "7d98984a": [
      2
    ],
    "2dc51cd8": [
      2
    ],
    "5242761d": [
      2
    ],
    "4a63824f": [
      2
    ],
    "8eb1e376": [
      2
    ],
    "9185454a": [
      3
    ],
    "b8e3ae1e": [
      3
    ],
    "1ed0af7e": [
      2
    ],
    "2aa4d300": [
      2
    ],
    "481be9a1": [
      2
    ],
    "3be7039a": [
      3
    ],
    "09c943bd": [
      2
    ],
    "6fe9f57e": [
      2
    ],
    "c24be16a": [
      2
    ],
    "069e0730": [
      2
    ],
    "78da33c3": [
      2
    ],
    "3b610782": [
      2
    ],
    "d6cadc9a": [
      2
    ],
    "67b09378": [
      3
    ],
    "b6b6dbca": [
      3
    ],
    "83ac1f80": [
      2
    ],
    "15cba8ca": [
      2
    ],
    "66ae95c7": [
      2
    ],
    "72c0782a": [
      2
    ],
    "aeaa5e54": [
      2
    ],
    "00e2d5a8": [
      2
    ],
    "1d781602": [
      2
    ],
    "7fa783f1": [
      3
    ],
    "227c8bcf": [
      2
    ],
    "1030f138": [
      2
    ],
    "a3ac672a": [
      2
    ],
    "29068ea4": [
      3
    ],
    "11a2a2f4": [
      2
    ],
    "392bc982": [
      2
    ],
    "08008eda": [
      0
    ],
    "d4069872": [
      2
    ],
    "3a2d2d72": [
      3
    ],
    "267f9866": [
      2
    ],
    "6f5168b8": [
      3
    ],
    "25062c92": [
      2
    ],
    "dc4f268e": [
      2
    ],
    "284c6240": [
      2
    ],
    "5bbaadda": [
      2
    ],
    "636bbc91": [
      2
    ],
    "b406df44": [
      2
    ],
    "444334ba": [
      2
    ],
    "de8d1b84": [
      2
    ],
    "752668db": [
      2
    ],
    "4006abd5": [
      2
    ],
    "8148cbac": [
      2
    ],
    "7da73870": [
      2
    ],
    "2ea586e5": [
      2
    ],
    "11ef1aae": [
      2
    ],
    "e8da8358": [
      2
    ],
    "daf668e4": [
      2
    ],
    "971bb39a": [
      2
    ],
    "65ba059e": [
      2
    ],
    "33ae6272": [
      2
    ],
    "05f51d3c": [
      1
    ],
    "908ee97c": [
      2
    ],
    "4a44423c": [
      2
    ],
    "5a1fc79e": [
      2
    ],
    "647eff69": [
      1
    ],
    "d5d4855c": [
      2
    ],
    "7cc44536": [
      2
    ],
    "c9a7850a": [
      2
    ],
    "c35998b6": [
      2
    ],
    "47b17a06": [
      3
    ],
    "87ee2e1e": [
      2
    ],
    "32b841be": [
      2
    ],
    "8c8a95f8": [
      2
    ],
    "65b7b527": [
      2
    ],
    "4c69e345": [
      2
    ],
    "f3d4b942": [
      2
    ],
    "72bebe26": [
      3
    ],
    "19b3f71d": [
      2
    ],
    "232e6bd6": [
      2
    ],
    "31d10da3": [
      2
    ],
    "503c3ff2": [
      2
    ],
    "3e6cb9af": [
      2
    ],
    "fe04d93c": [
      2
    ],
    "e3d6a9c6": [
      3
    ],
    "3277eac2": [
      2
    ],
    "acdb8412": [
      2
    ],
    "4b1cb828": [
      2
    ],
    "1d45330c": [
      2
    ],
    "2e0de3a0": [
      2
    ],
    "1c36d0d8": [
      2
    ],
    "f3248742": [
      2
    ],
    "a7cfb144": [
      3
    ]
  }
}